{
    "factions": [
        {
            "name": "Votann",
            "units": [
                {
                    "id": 1,
                    "name": "Ûthar le Destiné",
                    "points": 115,
                    "logo": "UtharLeDestine.jpeg",
                    "keywords": [
                        "Infanterie",
                        "Personnage",
                        "Héros Epique",
                        "Ûthar le Destiné"
                    ]
                },
                {
                    "id": 2,
                    "name": "Kâhl",
                    "points": 90,
                    "logo": "Kahl.jpeg",
                    "keywords": [
                        "Infanterie",
                        "Personnage",
                        "Kâhl"
                    ]
                },
                {
                    "id": 3,
                    "name": "Champion Einhyr",
                    "points": 75,
                    "logo": "ChampionEinhyr.jpeg",
                    "keywords": [
                        "Infanterie",
                        "Personnage",
                        "Exo-Scaphandre",
                        "Champion Einhyr"
                    ]
                },
                {
                    "id": 4,
                    "name": "Grimnyr",
                    "points": 75,
                    "logo": "Grimnyr.jpeg",
                    "keywords": [
                        "Infanterie",
                        "Grimnyr",
                        "Personnage",
                        "Psyker"
                    ]
                },
                {
                    "id": 5,
                    "name": "Maître-Fer Brôkhyr",
                    "points": 75,
                    "logo": "MaitreFerBrokhyr.jpeg",
                    "keywords": [
                        "Infanterie",
                        "Maître-Fer Brôkhyr",
                        "Personnage"
                    ]
                },
                {
                    "id": 6,
                    "name": "Guerriers Âtrekogs",
                    "points": 135,
                    "logo": "GuerriersAtrekogs.jpeg",
                    "keywords": [
                        "Infanterie",
                        "Ligne",
                        "Grenades",
                        "Guerriers Âtrekogs"
                    ],
                    "figurines": 10
                },
                {
                    "id": 7,
                    "name": "Âtregardes Einhyr",
                    "points": 165,
                    "logo": "AtregardesEinhyr.jpeg",
                    "keywords": [
                        "Infanterie",
                        "Exo-Scaphandre",
                        "Âtregardes Einhyrs"
                    ],
                    "options": [
                        {
                            "name": "Ajouter 5 figurines",
                            "points": 165
                        }
                    ],
                    "figurines": 5
                },
                {
                    "id": 8,
                    "name": "Beserks Cthoniens",
                    "points": 135,
                    "logo": "BeserksCthoniens.jpeg",
                    "keywords": [
                        "Infanterie",
                        "Beserks Cthoniens"
                    ],
                    "options": [
                        {
                            "name": "Ajouter 5 figurines",
                            "points": 135
                        }
                    ],
                    "figurines": 5
                },
                {
                    "id": 9,
                    "name": "Pionners Hernkogs",
                    "points": 105,
                    "logo": "PionniersHernkogs.jpeg",
                    "keywords": [
                        "Monté",
                        "Grenades",
                        "Vol",
                        "Pionners Hernkogs"
                    ],
                    "options": [
                        {
                            "name": "Ajouter 5 figurines",
                            "points": 105
                        }
                    ],
                    "figurines": 5
                },
                {
                    "id": 10,
                    "name": "Sagitaur",
                    "points": 120,
                    "logo": "Sagitaur.jpeg",
                    "keywords": [
                        "Véhicule",
                        "Transport",
                        "Transport Assigné",
                        "Sagitaur"
                    ]
                },
                {
                    "id": 11,
                    "name": "Tonnekogs Brokhyrs",
                    "points": 95,
                    "logo": "TonnekogsBrokhyrs.jpeg",
                    "keywords": [
                        "Infanterie",
                        "Exo-Chassis",
                        "Tonnekogs Brokhyrs"
                    ],
                    "options": [
                        {
                            "name": "Ajouter 3 figurines",
                            "points": 95
                        }
                    ],
                    "figurines": 3
                },
                {
                    "id": 12,
                    "name": "Forteresse Mobile Hekaton",
                    "points": 245,
                    "logo": "ForteresseMobileHekaton.jpeg",
                    "keywords": [
                        "Véhicule",
                        "Transport",
                        "Forteresse Mobile Hekaton"
                    ]
                }
            ]
        },
        {
            "name": "Marines Du Chaos",
            "units": [
                {
                    "id": 13,
                    "name": "Abaddon Le Fléau",
                    "points": 280,
                    "logo": "AbaddonLeFleau.jpeg",
                    "keywords": [
                        "Infanterie",
                        "Personnage",
                        "Héros Epique",
                        "Terminator",
                        "Chaos Universel",
                        "Chaos",
                        "Khorne",
                        "Slaanesh",
                        "Nurgle",
                        "Tzeentch",
                        "Abaddon Le Fléau"
                    ]
                },
                {
                    "id": 14,
                    "name": "Accusateur Rénégat",
                    "points": 65,
                    "figurines": 2,
                    "logo": "AccusateurRenegat.jpeg",
                    "keywords": [
                        "Infanterie",
                        "Chaos",
                        "Grenades",
                        "Personnage",
                        "Accusateur Renégat"
                    ]
                },
                {
                    "id": 15,
                    "name": "Apôtre Noir",
                    "points": 85,
                    "logo": "ApotreNoir.jpeg",
                    "keywords": [
                        "Infanterie",
                        "Grenades",
                        "Chaos",
                        "Personnage",
                        "Apôtre Noir"
                    ]
                },
                {
                    "id": 16,
                    "name": "Bande de Cultistes",
                    "points": 55,
                    "logo": "BandeDeCultistes.jpeg",
                    "keywords": [
                        "Infanterie",
                        "Ligne",
                        "Grenades",
                        "Chaos",
                        "Bande de Cultistes"
                    ],
                    "options": [
                        {
                            "name": "Ajouter 10 figurines",
                            "points": 55
                        }
                    ],
                    "figurines": 10
                },
                {
                    "id": 17,
                    "name": "Champion Exalté",
                    "points": 70,
                    "logo": "ChampionExalte.jpeg",
                    "keywords": [
                        "Infanterie",
                        "Personnage",
                        "Grenades",
                        "Chaos",
                        "Champion Exalté"
                    ]
                },
                {
                    "id": 18,
                    "name": "Couronne de Noctilithe",
                    "points": 125,
                    "logo": "CouronneDeNoctilithe.jpeg",
                    "keywords": [
                        "Fortification",
                        "Chaos",
                        "Couronne de Noctilithe"
                    ]
                },
                {
                    "id": 19,
                    "name": "Cultistes Maudits",
                    "points": 95,
                    "logo": "CultistesMaudits.jpeg",
                    "keywords": [
                        "Infanterie",
                        "Chaos",
                        "Cultistes Maudits"
                    ],
                    "options": [
                        {
                            "name": "Ajouter 8 figurines",
                            "points": 95
                        }
                    ],
                    "figurines": 8
                },
                {
                    "id": 20,
                    "name": "Cypher",
                    "points": 105,
                    "logo": "Cypher.jpeg",
                    "keywords": [
                        "Infanterie",
                        "Chaos",
                        "Personnage",
                        "Héros Epique",
                        "Cypher"
                    ]
                },
                {
                    "id": 21,
                    "name": "Escouade Terminator du Chaos",
                    "points": 195,
                    "logo": "EscouadeTerminatorDuChaos.jpeg",
                    "keywords": [
                        "Infanterie",
                        "Chaos",
                        "Terminator",
                        "Escouade Terminator du Chaos"
                    ],
                    "options": [
                        {
                            "name": "Ajouter 5 figurines",
                            "points": 195
                        }
                    ],
                    "figurines": 5
                },
                {
                    "id": 22,
                    "name": "Escouade de Gardes Renégats",
                    "points": 70,
                    "logo": "EscouadeDeGardesRenegats.jpeg",
                    "keywords": [
                        "Infanterie",
                        "Chaos",
                        "Grenades",
                        "Escouade de Gardes Renégats"
                    ],
                    "figurines": 10
                },
                {
                    "id": 23,
                    "name": "Fabius Bile",
                    "points": 100,
                    "logo": "FabiusBile.jpeg",
                    "keywords": [
                        "Infanterie",
                        "Chaos",
                        "Chaos Universel",
                        "Personnage",
                        "Héros Epique",
                        "Fabius Bile"
                    ],
                    "figurines": 2
                },
                {
                    "id": 24,
                    "name": "Ferrocentaurus",
                    "points": 165,
                    "logo": "Ferrocentaurus.jpeg",
                    "keywords": [
                        "Véhicule",
                        "Marcheur",
                        "Chaos",
                        "Démon",
                        "Ferrocentaurus"
                    ]
                },
                {
                    "id": 25,
                    "name": "Ferrocerberus",
                    "points": 155,
                    "logo": "Ferrocerberus.jpeg",
                    "keywords": [
                        "Véhicule",
                        "Marcheur",
                        "Chaos",
                        "Démon",
                        "Ferrocerberus"
                    ]
                },
                {
                    "id": 26,
                    "name": "Haarken Worldclaimer",
                    "points": 120,
                    "logo": "HaarkenWorldclaimer.jpeg",
                    "keywords": [
                        "Infanterie",
                        "Chaos",
                        "Personnage",
                        "Héros Epique",
                        "Vol",
                        "Réacteur Dorsal",
                        "Chaos Universel",
                        "Haarken Worldclaimer"
                    ]
                },
                {
                    "id": 27,
                    "name": "Havocs",
                    "points": 135,
                    "logo": "Havocs.jpeg",
                    "keywords": [
                        "Infanterie",
                        "Chaos",
                        "Havocs"
                    ]
                },
                {
                    "id": 28,
                    "name": "Hommes-bêtes Affregors",
                    "points": 95,
                    "logo": "HommesBetesAffregors.jpeg",
                    "keywords": [
                        "Infanterie",
                        "Chaos",
                        "Terminator",
                        "Escouade Terminator du Chaos"
                    ]
                },
                {
                    "id": 29,
                    "name": "Huron Blackheart",
                    "points": 80,
                    "logo": "HuronBlackheart.jpeg",
                    "keywords": [
                        "Infanterie",
                        "Chaos",
                        "Terminator",
                        "Escouade Terminator du Chaos"
                    ]
                },
                {
                    "id": 30,
                    "name": "Land Raider du Chaos",
                    "points": 255,
                    "logo": "LandRaiderDuChaos.jpeg",
                    "keywords": [
                        "Infanterie",
                        "Chaos",
                        "Terminator",
                        "Escouade Terminator du Chaos"
                    ]
                },
                {
                    "id": 31,
                    "name": "Lucius L'Eternel",
                    "points": 95,
                    "logo": "LuciusLeternel.jpeg",
                    "keywords": [
                        "Infanterie",
                        "Chaos",
                        "Terminator",
                        "Escouade Terminator du Chaos"
                    ]
                },
                {
                    "id": 32,
                    "name": "Légionnaires",
                    "points": 100,
                    "logo": "Legionnaires.jpeg",
                    "keywords": [
                        "Infanterie",
                        "Chaos",
                        "Terminator",
                        "Escouade Terminator du Chaos"
                    ],
                    "options": [
                        {
                            "name": "Ajouter 5 figurines",
                            "points": 100
                        }
                    ],
                    "figurines": 5
                },
                {
                    "id": 33,
                    "name": "Marines du Vacarme",
                    "points": 85,
                    "logo": "MarinesDuVacarme.jpeg",
                    "keywords": [
                        "Infanterie",
                        "Chaos",
                        "Terminator",
                        "Escouade Terminator du Chaos"
                    ],
                    "options": [
                        {
                            "name": "Ajouter 5 figurines",
                            "points": 85
                        }
                    ],
                    "figurines": 5
                },
                {
                    "id": 34,
                    "name": "Maître de la Possession",
                    "points": 70,
                    "logo": "MaitreDeLaPossession.jpeg",
                    "keywords": [
                        "Infanterie",
                        "Chaos",
                        "Terminator",
                        "Escouade Terminator du Chaos"
                    ]
                },
                {
                    "id": 35,
                    "name": "Maître des Exécutions",
                    "points": 80,
                    "logo": "MaitreDesExecutions.jpeg",
                    "keywords": [
                        "Infanterie",
                        "Chaos",
                        "Terminator",
                        "Escouade Terminator du Chaos"
                    ]
                },
                {
                    "id": 36,
                    "name": "Motards du Chaos",
                    "points": 95,
                    "logo": "MotardsDuChaos.jpeg",
                    "keywords": [
                        "Infanterie",
                        "Chaos",
                        "Terminator",
                        "Escouade Terminator du Chaos"
                    ],
                    "options": [
                        {
                            "name": "Ajouter 3 figurines",
                            "points": 95
                        }
                    ],
                    "figurines": 3
                },
                {
                    "id": 37,
                    "name": "Métabrutus",
                    "points": 155,
                    "logo": "Metabrutus.jpeg",
                    "keywords": [
                        "Infanterie",
                        "Chaos",
                        "Terminator",
                        "Escouade Terminator du Chaos"
                    ]
                },
                {
                    "id": 38,
                    "name": "Métadrak",
                    "points": 205,
                    "logo": "Metadrak.jpeg",
                    "keywords": [
                        "Infanterie",
                        "Chaos",
                        "Terminator",
                        "Escouade Terminator du Chaos"
                    ]
                },
                {
                    "id": 39,
                    "name": "Métaragne",
                    "points": 140,
                    "logo": "Metaragne.jpeg",
                    "keywords": [
                        "Infanterie",
                        "Chaos",
                        "Terminator",
                        "Escouade Terminator du Chaos"
                    ]
                },
                {
                    "id": 40,
                    "name": "Obliterators",
                    "points": 160,
                    "logo": "Obliterators.jpeg",
                    "keywords": [
                        "Infanterie",
                        "Chaos",
                        "Terminator",
                        "Escouade Terminator du Chaos"
                    ],
                    "options": [
                        {
                            "name": "Ajouter 2 figurines",
                            "points": 160
                        }
                    ],
                    "figurines": 2
                },
                {
                    "id": 41,
                    "name": "Possédés",
                    "points": 145,
                    "logo": "Possedes.jpeg",
                    "keywords": [
                        "Infanterie",
                        "Chaos",
                        "Terminator",
                        "Escouade Terminator du Chaos"
                    ],
                    "options": [
                        {
                            "name": "Ajouter 5 figurines",
                            "points": 145
                        }
                    ],
                    "figurines": 5
                },
                {
                    "id": 42,
                    "name": "Predator Annihilator du Chaos",
                    "points": 135,
                    "logo": "PredatorAnnihilatorDuChaos.jpeg",
                    "keywords": [
                        "Infanterie",
                        "Chaos",
                        "Terminator",
                        "Escouade Terminator du Chaos"
                    ]
                },
                {
                    "id": 43,
                    "name": "Predator Destructor du Chaos",
                    "points": 130,
                    "logo": "PredatorDestructorDuchaos.jpeg",
                    "keywords": [
                        "Infanterie",
                        "Chaos",
                        "Terminator",
                        "Escouade Terminator du Chaos"
                    ]
                },
                {
                    "id": 44,
                    "name": "Prince Démon de l'Hereticus Astartes",
                    "points": 180,
                    "logo": "PrinceDemonDelHereticusAstartes.jpeg",
                    "keywords": [
                        "Infanterie",
                        "Chaos",
                        "Terminator",
                        "Escouade Terminator du Chaos"
                    ]
                },
                {
                    "id": 45,
                    "name": "Prince Démon de l'Hereticus Astartes Ailé",
                    "points": 195,
                    "logo": "PrinceDemonDelHereticusAstartesAile.jpeg",
                    "keywords": [
                        "Infanterie",
                        "Chaos",
                        "Terminator",
                        "Escouade Terminator du Chaos"
                    ]
                },
                {
                    "id": 46,
                    "name": "Profanateur",
                    "points": 210,
                    "logo": "Profanateur.jpeg",
                    "keywords": [
                        "Infanterie",
                        "Chaos",
                        "Terminator",
                        "Escouade Terminator du Chaos"
                    ]
                },
                {
                    "id": 47,
                    "name": "Rapaces",
                    "points": 95,
                    "logo": "Rapaces.jpeg",
                    "keywords": [
                        "Infanterie",
                        "Chaos",
                        "Terminator",
                        "Escouade Terminator du Chaos"
                    ],
                    "options": [
                        {
                            "name": "Ajouter 5 figurines",
                            "points": 95
                        }
                    ],
                    "figurines": 5
                },
                {
                    "id": 48,
                    "name": "Rejetons du Chaos",
                    "points": 80,
                    "logo": "RejetonsDuChaos.jpeg",
                    "keywords": [
                        "Infanterie",
                        "Chaos",
                        "Terminator",
                        "Escouade Terminator du Chaos"
                    ],
                    "figurines": 2
                },
                {
                    "id": 49,
                    "name": "Rhino du Chaos",
                    "points": 85,
                    "logo": "RhinoDuChaos.jpeg",
                    "keywords": [
                        "Infanterie",
                        "Chaos",
                        "Terminator",
                        "Escouade Terminator du Chaos"
                    ]
                },
                {
                    "id": 50,
                    "name": "Seigneur de la Discorde sur Métarôdeur",
                    "points": 220,
                    "logo": "SeigneurDeLaDiscordeSurMetarodeur.jpeg",
                    "keywords": [
                        "Infanterie",
                        "Chaos",
                        "Terminator",
                        "Escouade Terminator du Chaos"
                    ]
                },
                {
                    "id": 51,
                    "name": "Seigneur des Crânes de Khorne",
                    "points": 420,
                    "logo": "SeigneurDesCranesDeKhorne.jpeg",
                    "keywords": [
                        "Infanterie",
                        "Chaos",
                        "Terminator",
                        "Escouade Terminator du Chaos"
                    ]
                },
                {
                    "id": 52,
                    "name": "Seigneur du Chaos",
                    "points": 75,
                    "logo": "SeigneurDuChaos.jpeg",
                    "keywords": [
                        "Infanterie",
                        "Chaos",
                        "Terminator",
                        "Escouade Terminator du Chaos"
                    ]
                },
                {
                    "id": 53,
                    "name": "Seigneur du Chaos en Armure Terminator",
                    "points": 100,
                    "logo": "SeigneurDuChaosEnArmureTerminator.jpeg",
                    "keywords": [
                        "Infanterie",
                        "Chaos",
                        "Terminator",
                        "Escouade Terminator du Chaos"
                    ]
                },
                {
                    "id": 54,
                    "name": "Serres du Warp",
                    "points": 130,
                    "logo": "SerresDuWarp.jpeg",
                    "keywords": [
                        "Infanterie",
                        "Chaos",
                        "Terminator",
                        "Escouade Terminator du Chaos"
                    ],
                    "options": [
                        {
                            "name": "Ajouter 5 figurines",
                            "points": 130
                        }
                    ],
                    "figurines": 5
                },
                {
                    "id": 55,
                    "name": "Sombre Communion",
                    "points": 5,
                    "logo": "SombreCommunion.jpeg",
                    "keywords": [
                        "Infanterie",
                        "Chaos",
                        "Terminator",
                        "Escouade Terminator du Chaos"
                    ],
                    "figurines": 5
                },
                {
                    "id": 56,
                    "name": "Sorcier",
                    "points": 60,
                    "logo": "Sorcier.jpeg",
                    "keywords": [
                        "Infanterie",
                        "Chaos",
                        "Terminator",
                        "Escouade Terminator du Chaos"
                    ]
                },
                {
                    "id": 57,
                    "name": "Sorcier en Armure Terminator",
                    "points": 90,
                    "logo": "SorcierEnArmureTerminator.jpeg",
                    "keywords": [
                        "Infanterie",
                        "Chaos",
                        "Terminator",
                        "Escouade Terminator du Chaos"
                    ]
                },
                {
                    "id": 58,
                    "name": "Techmancien",
                    "points": 70,
                    "logo": "Technmancien.jpeg",
                    "keywords": [
                        "Infanterie",
                        "Chaos",
                        "Terminator",
                        "Escouade Terminator du Chaos"
                    ]
                },
                {
                    "id": 59,
                    "name": "Vashtorr l'Arkifane",
                    "points": 225,
                    "logo": "VashtorrLArkifane.jpeg",
                    "keywords": [
                        "Infanterie",
                        "Chaos",
                        "Terminator",
                        "Escouade Terminator du Chaos"
                    ]
                },
                {
                    "id": 60,
                    "name": "Vindicator du Chaos",
                    "points": 210,
                    "logo": "VindicatorDuChaos.jpeg",
                    "keywords": [
                        "Infanterie",
                        "Chaos",
                        "Terminator",
                        "Escouade Terminator du Chaos"
                    ]
                },
                {
                    "id": 61,
                    "name": "Elus",
                    "points": 115,
                    "logo": "Elus.jpeg",
                    "keywords": [
                        "Infanterie",
                        "Chaos",
                        "Terminator",
                        "Escouade Terminator du Chaos"
                    ],
                    "options": [
                        {
                            "name": "Ajouter 5 figurines",
                            "points": 115
                        }
                    ],
                    "figurines": 5
                }
            ]
        }
    ]
}